peloton_API/__init__.py
peloton_API/pelotonAPI_commonFunctions.py
peloton_API/siteview.py
peloton_API/wellview.py
pelotonKODArestAPI-0.1.6.dist-info/LICENSE.txt
pelotonKODArestAPI-0.1.6.dist-info/METADATA
pelotonKODArestAPI-0.1.6.dist-info/WHEEL
pelotonKODArestAPI-0.1.6.dist-info/top_level.txt
pelotonKODArestAPI-0.1.6.dist-info/RECORD
