Metadata-Version: 2.1
Name: pelotonKODArestAPI
Version: 0.1.6
Summary: Package built to utilize the Peloton Platform API (wellView, siteView etc)
Home-page: https://github.com/pypa/sampleproject
Author: Evan Rynearson
Author-email: evan.rynearson@kodares.com
Project-URL: Bug Tracker, https://github.com/pypa/sampleproject/issues
Classifier: Programming Language :: Python :: 3
Classifier: License :: OSI Approved :: MIT License
Classifier: Operating System :: OS Independent
Requires-Python: >=3.6
License-File: LICENSE.txt
